<?xml version="1.0" encoding="UTF-8"?>
<Patch>
	<!-- TEMPERATE FOREST -->
	<Operation Class="PatchOperationReplace">
		<xpath>Defs/BiomeDef[defName="TemperateForest"]/terrainsByFertility</xpath>
		<value>
			<terrainsByFertility>
				<li>
					<terrain>Soil</terrain>
					<min>-999</min>
					<max>0.6</max>
				</li>
				<li>
					<terrain>RedClaySoil</terrain>
					<min>0.6</min>
					<max>999</max>
				</li>
			</terrainsByFertility>
		</value>
    </Operation>	
	
	<Operation Class="PatchOperationReplace">
		<xpath>Defs/BiomeDef[defName="TemperateForest"]/terrainPatchMakers</xpath>
		<value>
			<terrainPatchMakers>
				<li>
					<perlinFrequency>0.015</perlinFrequency>
					<thresholds>
						<li>
							<terrain>SoilRich</terrain>
							<min>0.60</min>
							<max>0.75</max>
						</li>
						<li>
							<terrain>WaterShallow</terrain>
							<min>0.75</min>
							<max>0.85</max>
						</li>
						<li>
							<terrain>WaterDeep</terrain>
							<min>0.85</min>
							<max>999</max>
						</li>
					</thresholds>
				</li>
				<li>
					<perlinFrequency>0.003</perlinFrequency>
					<thresholds>
						<li>
							<terrain>MarshyTerrain</terrain>
							<min>0.9</min>
							<max>0.95</max>
						</li>
						<li>
							<terrain>SwampWater</terrain>
							<min>0.95</min>
							<max>999</max>
						</li>
					</thresholds>
				</li>
				<li>
					<perlinFrequency>0.02</perlinFrequency>
					<thresholds>
						<li>
							<terrain>Gravel</terrain> <!-- Weak Soil -->
							<min>0.11</min>
							<max>0.2</max>
						</li>
					</thresholds>
				</li>
			</terrainPatchMakers>
		</value>
    </Operation>	
	<!-- TAIGA -->
	<Operation Class="PatchOperationReplace">
		<xpath>Defs/BiomeDef[defName="BorealForest"]/terrainsByFertility</xpath>
		<value>
			<terrainsByFertility>
				<li>
					<terrain>MossyTerrain</terrain>
					<min>-999</min>
					<max>0.75</max>
				</li>
                <li>
					<terrain>Soil</terrain>
					<min>0.75</min>
					<max>999</max>
				</li>
			</terrainsByFertility>
		</value>
    </Operation>	
	
	<Operation Class="PatchOperationReplace">
		<xpath>Defs/BiomeDef[defName="BorealForest"]/terrainPatchMakers</xpath>
		<value>
			<terrainPatchMakers>
				<li>
					<perlinFrequency>0.02</perlinFrequency>
					<thresholds>
						<li>
							<terrain>MossyTerrain</terrain>
							<min>0.4</min>
							<max>0.6</max>
						</li>
						<li>
							<terrain>SoilRich</terrain>
							<min>0.6</min>
							<max>0.5</max>
						</li>
						<li>
							<terrain>WaterShallow</terrain>
							<min>0.5</min>
							<max>0.5</max>
						</li>
						<li>
							<terrain>WaterDeep</terrain>
							<min>0.95</min>
							<max>1.24</max>
						</li>
					</thresholds>
				</li>
				<!--<li>
					<perlinFrequency>0.01</perlinFrequency>
					<thresholds>
						<li>
							<terrain>Mud</terrain>
							<min>0.9</min>
							<max>0.95</max>
						</li>
						<li>
							<terrain>BogWater</terrain>
							<min>0.95</min>
							<max>1.2</max>
						</li>
					</thresholds>
				</li>-->
				<li>
					<perlinFrequency>0.02</perlinFrequency>
					<thresholds>
						<li>
							<terrain>WeakSoil</terrain> <!-- Weak Soil -->
							<min>0.11</min>
							<max>0.7</max>
						</li>
					</thresholds>
				</li>
			</terrainPatchMakers>
		</value>
    </Operation>	
	
	<!-- TUNDRA -->
	<Operation Class="PatchOperationReplace">
		<xpath>Defs/BiomeDef[defName="Tundra"]/terrainsByFertility</xpath>
		<value>
			<terrainsByFertility>
				<li>
					<terrain>MossyTerrain</terrain>
					<min>-999</min>
					<max>999</max>
				</li>
			</terrainsByFertility>
		</value>
    </Operation>	
	
	<Operation Class="PatchOperationReplace">
		<xpath>Defs/BiomeDef[defName="Tundra"]/terrainPatchMakers</xpath>
		<value>
			<terrainPatchMakers>
				<li>
					<perlinFrequency>0.004</perlinFrequency>
					<thresholds>
						<li>
							<terrain>PeatSoil</terrain>
							<min>-0.05</min>
							<max>0.01</max>
						</li>
					</thresholds>
				</li>
				<li>
					<perlinFrequency>0.04</perlinFrequency>
					<thresholds>
						<li>
							<terrain>PoorSoil</terrain>
							<min>0.03</min>
							<max>0.55</max>
						</li>
					</thresholds>
				</li>
				<li>
					<perlinFrequency>0.003</perlinFrequency>
					<thresholds>
						<li>
							<terrain>WaterShallow</terrain>
							<min>0.55</min>
							<max>0.62</max>
						</li>
					</thresholds>
				</li>
				
			</terrainPatchMakers>
		</value>
    </Operation>	
	
	<!-- ICE SHEET -->
	<Operation Class="PatchOperationReplace">
		<xpath>Defs/BiomeDef[defName="IceSheet"]/terrainsByFertility</xpath>
		<value>
			<terrainsByFertility>
				<li>
					<terrain>Ice</terrain>
					<min>-999</min>
					<max>0.5</max>
				</li>
				<li>
					<terrain>FrozenSnow</terrain>
					<min>0.5</min>
					<max>999</max>
				</li>
			</terrainsByFertility>
		</value>
    </Operation>	
	
	<Operation Class="PatchOperationReplace">
		<xpath>Defs/BiomeDef[defName="IceSheet"]/terrainPatchMakers</xpath>
		<value>
			<terrainPatchMakers>
			<li>
				<perlinFrequency>0.025</perlinFrequency>
				<thresholds>
					<li>
						<terrain>IceClear</terrain>
						<min>0.40</min>
						<max>0.76</max>
					</li>
					<li>
						<terrain>WaterShallow</terrain>
						<min>0.76</min>
						<max>0.98</max>
					</li>
					<li>
						<terrain>WaterDeep</terrain>
						<min>0.98</min>
						<max>999</max>
					</li>
				</thresholds>
			</li>
			<li>
				<perlinFrequency>0.01</perlinFrequency>
				<thresholds>
					<li>
						<terrain>PoorSoil</terrain>
						<min>0.87</min>
						<max>1.0</max>
					</li>
				</thresholds>
			</li>
			
		</terrainPatchMakers>
		</value>
    </Operation>	
		<!-- SEA ICE -->
	<Operation Class="PatchOperationReplace">
		<xpath>Defs/BiomeDef[defName="SeaIce"]/terrainsByFertility</xpath>
		<value>
			<terrainsByFertility>
				<li>
					<terrain>Ice</terrain>
					<min>-999</min>
					<max>0.4</max>
				</li>
				<li>
					<terrain>FrozenSnow</terrain>
					<min>0.4</min>
					<max>999</max>
				</li>
			</terrainsByFertility>
		</value>
    </Operation>	
	
	<Operation Class="PatchOperationReplace">
		<xpath>Defs/BiomeDef[defName="SeaIce"]/terrainPatchMakers</xpath>
		<value>
			<terrainPatchMakers>
			<li>
				<perlinFrequency>0.025</perlinFrequency>
				<thresholds>
					<li>
						<terrain>WaterShallow</terrain>
						<min>0.76</min>
						<max>0.98</max>
					</li>
					<li>
						<terrain>WaterDeep</terrain>
						<min>0.98</min>
						<max>1.0</max>
					</li>
				</thresholds>
			</li>
			<li>
				<perlinFrequency>0.03</perlinFrequency>
				<thresholds>
					<li>
						<terrain>IceClear</terrain>
						<min>0.30</min>
						<max>0.7</max>
					</li>
					<li>
						<terrain>WaterDeep</terrain>
						<min>0.7</min>
						<max>1.12</max>
					</li>
				</thresholds>
			</li>
			<li>
				<perlinFrequency>0.06</perlinFrequency>
				<thresholds>
					<li>
						<terrain>Ice</terrain>
						<min>0.6</min>
						<max>0.7</max>
					</li>
					<li>
						<terrain>IceClear</terrain>
						<min>0.7</min>
						<max>1.0</max>
					</li>
				</thresholds>
			</li>
		</terrainPatchMakers>
		</value>
    </Operation>	
	
</Patch>