<?xml version="1.0" encoding="utf-8" ?>
<Defs>

	<BiomeDef>
		<defName>Prairie</defName>
		<label>prairie</label>
		<description>Prairies are a type of temperate grassland. As the name suggests, it's mostly grass and sedge, with a few interspersed willows and oaks.</description>	
		<workerClass>BiomesKit.UniversalBiomeWorker</workerClass>
        <modExtensions>
            <li Class="BiomesKit.BiomesKitControls">
                  <randomizeHilliness>False</randomizeHilliness>
                  <usePerlin>True</usePerlin>
                  <perlinCulling>0.5</perlinCulling>
                  <minTemperature>-10</minTemperature>
                  <maxTemperature>30</maxTemperature>
                  <minRainfall>300</minRainfall>
                  <frequency>30</frequency>
                  <spawnOnBiomes>
                    <li>TemperateForest</li>
                </spawnOnBiomes>
            </li>
        </modExtensions>
		<animalDensity>2.8</animalDensity>
		<plantDensity>1.5</plantDensity>
		<settlementSelectionWeight>0.85</settlementSelectionWeight>
		<movementDifficulty>1</movementDifficulty>
		<texture>World/Biomes/Grassland</texture>
		<forageability>0.7</forageability>
		<foragedFood>RawBerries</foragedFood>
		<wildPlantRegrowDays>25</wildPlantRegrowDays>
		<soundsAmbient>
			<li>Ambient_NightInsects_Standard</li>
		</soundsAmbient>
		<diseaseMtbDays>60</diseaseMtbDays>
		<diseases>
			<li>
				<diseaseInc>Disease_CommonCold</diseaseInc>
				<commonality>100</commonality>
			</li>
			<li>
				<diseaseInc>Disease_strepthroat</diseaseInc>
				<commonality>100</commonality>
			</li>
			<li>
				<diseaseInc>Disease_earache</diseaseInc>
				<commonality>100</commonality>
			</li>
			<li>
				<diseaseInc>Disease_Flu</diseaseInc>
				<commonality>100</commonality>
			</li>
			<li>
				<diseaseInc>Disease_Plague</diseaseInc>
				<commonality>100</commonality>
			</li>
			<li>
				<diseaseInc>Disease_Malaria</diseaseInc>
				<commonality>100</commonality>
			</li>
			<li>
				<diseaseInc>Disease_Fever</diseaseInc>
				<commonality>100</commonality>
			</li>
			<li>
				<diseaseInc>Disease_Measles</diseaseInc>
				<commonality>100</commonality>
			</li>
			<li>
				<diseaseInc>Disease_Ebola</diseaseInc>
				<commonality>20</commonality>
			</li>
			<li>
				<diseaseInc>Disease_Pneumonia</diseaseInc>
				<commonality>50</commonality>
			</li>
			<li>
				<diseaseInc>Disease_FibrousMechanites</diseaseInc>
				<commonality>30</commonality>
			</li>
			<li>
				<diseaseInc>Disease_SensoryMechanites</diseaseInc>
				<commonality>30</commonality>
			</li>
			<li>
				<diseaseInc>Disease_GutWorms</diseaseInc>
				<commonality>50</commonality>
			</li>
			<li>
				<diseaseInc>Disease_MuscleParasites</diseaseInc>
				<commonality>50</commonality>
			</li>
			<li>
				<diseaseInc>Disease_AnimalFlu</diseaseInc>
				<commonality>100</commonality>
			</li>
			<li>
				<diseaseInc>Disease_AnimalPlague</diseaseInc>
				<commonality>100</commonality>
			</li>
		</diseases>
		<terrainsByFertility>
			<li>
				<terrain>Gravel</terrain>
				<min>-999</min>
				<max>0.10</max>
			</li>
			<li>
				<terrain>PrairieSoil</terrain>
				<min>0.1</min>
				<max>0.7</max>
			</li>
            <li>
				<terrain>SavannaSoil</terrain>
				<min>0.7</min>
				<max>999</max>
			</li>
		</terrainsByFertility>
		<terrainPatchMakers>
			<li>
				<perlinFrequency>0.015</perlinFrequency>
				<thresholds>
					<li>
						<terrain>SoilRich</terrain>
						<min>0.93</min>
						<max>1.12</max>
					</li>
					<li>
						<terrain>WaterShallow</terrain>
						<min>1.12</min>
						<max>999</max>
					</li>
				</thresholds>
			</li>
		</terrainPatchMakers>
		<baseWeatherCommonalities>
			<Clear>18</Clear>
			<Fog>1</Fog>
			<Rain>2</Rain>
			<DryThunderstorm>1</DryThunderstorm>
			<RainyThunderstorm>2</RainyThunderstorm>
			<FoggyRain>1</FoggyRain>
			<SnowGentle>4</SnowGentle>
			<SnowHard>4</SnowHard>
			<Rainstorm>1</Rainstorm>
			<Blizzard>3</Blizzard>
			<Whiteout>1</Whiteout>
			<Hurricane>0.2</Hurricane>
			<!--<DryDuststorm>1</DryDuststorm>
			<DustStorm>1</DustStorm>-->
		</baseWeatherCommonalities>
		<wildPlants>
			<Plantwheat>0.08</Plantwheat>
			<Plant_Flax>0.08</Plant_Flax>
			<Plant_Berry>0.15</Plant_Berry>
			<!--<Plant_TreeApple>0.10</Plant_TreeApple>
			<Plant_TreePeach>0.08</Plant_TreePeach>-->
			<Plant_TreeGrape>0.08</Plant_TreeGrape>
			<Plant_Bush>1</Plant_Bush>
			<Plant_Rhododendron>0.25</Plant_Rhododendron>
			<Plant_Healroot>0.1</Plant_Healroot>
			<Plant_Grass>12</Plant_Grass>
            <Plant_Sedge>6</Plant_Sedge>    
			<Plant_Brambles>0.4</Plant_Brambles>
			<Plant_Daylily>0.3</Plant_Daylily>
			<Plant_Astragalus>0.2</Plant_Astragalus>
			<Plant_Dandelion>1</Plant_Dandelion>
			<Plant_Anthurium>0.02</Plant_Anthurium>
			<Plant_Venus>0.2</Plant_Venus>
			<Plant_Crocus>0.5</Plant_Crocus>
			<Plant_Mushroom_Blue>0.02</Plant_Mushroom_Blue>
			<Plant_Mushroom_Red>0.02</Plant_Mushroom_Red>
			<Plant_Mushroom>0.1</Plant_Mushroom>
			<Plant_WhiteRose>0.13</Plant_WhiteRose>
			<Plant_TreeOak>0.1</Plant_TreeOak>
            <Plant_TreePoplar>0.08</Plant_TreePoplar>
			<Plant_TreeWillow>0.15</Plant_TreeWillow>
		</wildPlants>
		<wildAnimals>
			<Gazelle>0.1</Gazelle>
			<Ibex>0.35</Ibex>
			<Deer>0.55</Deer>
			<Muffalo>0.45</Muffalo>
			<Alpaca>0.1</Alpaca>
			<Squirrel>1</Squirrel>
			<WildBoar>0.6</WildBoar>
			<Boomrat>0.25</Boomrat>
			<Tortoise>0.4</Tortoise>
			<Hare>1</Hare>
			<Boomalope>0.03</Boomalope>
			<Emu>0.1</Emu>
			<Turkey>0.5</Turkey>
			<Ostrich>0.2</Ostrich>
			<Rat>0.8</Rat>
			<Chipmunk>0.8</Chipmunk>
			<Fishercat>0.15</Fishercat>
			<Horse>0.08</Horse>
			<Raccoon>0.45</Raccoon>
			<Megasloth>0.04</Megasloth>
			<Warg>0.03</Warg>
			<Bear_Grizzly>0.06</Bear_Grizzly>
			<Cougar>0.03</Cougar>
			<Lynx>0.02</Lynx>
			<Wolf_Timber>0.08</Wolf_Timber>
			<Fox_Red>0.06</Fox_Red>
			<Nightling>0.03</Nightling>
			<Crashbug>1.2</Crashbug>
			<SmilodonPop>0.03</SmilodonPop>
			<Rimwolf>0.04</Rimwolf>
			<Terramorph>0.03</Terramorph>
			<Sheep>0.35</Sheep>
			<Fly>1.1</Fly>
			<Mosquito>1.1</Mosquito>
			<Buffalo>0.2</Buffalo>
			<Tiger>0.06</Tiger>
			<WhiteTiger>0.05</WhiteTiger>
			<SnowLeopard>0.07</SnowLeopard>
			<Cockroach>0.1</Cockroach>
		</wildAnimals>
		<allowedPackAnimals>
			<li>Muffalo</li>
			<li>Buffalo</li>
			<li>Horse</li>
			<li>Bear_Grizzly</li>
		</allowedPackAnimals>
	</BiomeDef>
    
    <BiomeDef>
		<defName>MontaneForest</defName>
		<label>montane forest</label>
		<description>Montane forest biomes are a found at mid-elevations. Not as dense as boreal forest and has no hardwood trees, though high rainfall leads to fast growth. May contain lakes.</description>	
		<workerClass>BiomesKit.UniversalBiomeWorker</workerClass>
        <modExtensions>
            <li Class="BiomesKit.BiomesKitControls">
                  <randomizeHilliness>True</randomizeHilliness>
                  <usePerlin>True</usePerlin>
                  <perlinCulling>0.5</perlinCulling>
                <minElevation>650</minElevation>
                <maxElevation>850</maxElevation>
                <spawnOnBiomes>
                    <li>BorealForest</li>
                    <li>ColdBog</li>
                </spawnOnBiomes>
                  <minRainfall>300</minRainfall>
                  <frequency>100</frequency>
            </li>
        </modExtensions>
		<animalDensity>2.5</animalDensity>
		<plantDensity>0.9</plantDensity>
		<settlementSelectionWeight>0.85</settlementSelectionWeight>
		<movementDifficulty>1</movementDifficulty>
		<texture>World/Biomes/MontaneForest</texture>
		<forageability>0.7</forageability>
		<foragedFood>RawBerries</foragedFood>
		<wildPlantRegrowDays>25</wildPlantRegrowDays>
		<soundsAmbient>
			<li>Ambient_NightInsects_Standard</li>
		</soundsAmbient>
		<diseaseMtbDays>60</diseaseMtbDays>
		<diseases>
			<li>
				<diseaseInc>Disease_CommonCold</diseaseInc>
				<commonality>100</commonality>
			</li>
			<li>
				<diseaseInc>Disease_strepthroat</diseaseInc>
				<commonality>100</commonality>
			</li>
			<li>
				<diseaseInc>Disease_earache</diseaseInc>
				<commonality>100</commonality>
			</li>
			<li>
				<diseaseInc>Disease_Flu</diseaseInc>
				<commonality>100</commonality>
			</li>
			<li>
				<diseaseInc>Disease_Plague</diseaseInc>
				<commonality>100</commonality>
			</li>
			<li>
				<diseaseInc>Disease_Malaria</diseaseInc>
				<commonality>100</commonality>
			</li>
			<li>
				<diseaseInc>Disease_Fever</diseaseInc>
				<commonality>100</commonality>
			</li>
			<li>
				<diseaseInc>Disease_Measles</diseaseInc>
				<commonality>100</commonality>
			</li>
			<li>
				<diseaseInc>Disease_Ebola</diseaseInc>
				<commonality>20</commonality>
			</li>
			<li>
				<diseaseInc>Disease_Pneumonia</diseaseInc>
				<commonality>50</commonality>
			</li>
			<li>
				<diseaseInc>Disease_FibrousMechanites</diseaseInc>
				<commonality>30</commonality>
			</li>
			<li>
				<diseaseInc>Disease_SensoryMechanites</diseaseInc>
				<commonality>30</commonality>
			</li>
			<li>
				<diseaseInc>Disease_GutWorms</diseaseInc>
				<commonality>50</commonality>
			</li>
			<li>
				<diseaseInc>Disease_MuscleParasites</diseaseInc>
				<commonality>50</commonality>
			</li>
			<li>
				<diseaseInc>Disease_AnimalFlu</diseaseInc>
				<commonality>100</commonality>
			</li>
			<li>
				<diseaseInc>Disease_AnimalPlague</diseaseInc>
				<commonality>100</commonality>
			</li>
		</diseases>
		<terrainsByFertility>
			<li>
				<terrain>Gravel</terrain>
				<min>-999</min>
				<max>0.15</max>
			</li>
			<li>
				<terrain>WeakSoil</terrain>
				<min>0.15</min>
				<max>0.45</max>
			</li>
            <li>
				<terrain>PrairieSoil</terrain>
				<min>0.45</min>
				<max>0.75</max>
			</li>
			<li>
				<terrain>VolcanicSoil</terrain>
				<min>0.75</min>
				<max>999</max>
			</li>
		</terrainsByFertility>
		<terrainPatchMakers>    
            <li>
				<perlinFrequency>0.015</perlinFrequency>
				<thresholds>
					<li>
						<terrain>Gravel</terrain>
						<min>0.95</min>
						<max>1.0</max>
					</li>
				</thresholds>
			</li>
            
			<li>
				<perlinFrequency>0.011</perlinFrequency>
				<thresholds>
					<li>
						<terrain>SoilRich</terrain>
						<min>0.7</min>
						<max>0.8</max>
					</li>
					<li>
						<terrain>WaterShallow</terrain>
						<min>0.8</min>
						<max>999</max>
					</li>
                    <li>
						<terrain>WaterDeep</terrain>
						<min>0.9</min>
						<max>999</max>
					</li>
				</thresholds>
			</li>
		</terrainPatchMakers>
		<baseWeatherCommonalities>
			<Clear>15</Clear>
			<Fog>4</Fog>
			<Rain>4</Rain>
			<DryThunderstorm>1</DryThunderstorm>
			<RainyThunderstorm>2</RainyThunderstorm>
			<FoggyRain>3</FoggyRain>
			<SnowGentle>4</SnowGentle>
			<SnowHard>4</SnowHard>
			<Rainstorm>3</Rainstorm>
			<Blizzard>4</Blizzard>
			<Whiteout>4</Whiteout>
			<Hurricane>0.1</Hurricane>
		</baseWeatherCommonalities>
		<wildPlants>
            <Plant_TreeGrape>0.06</Plant_TreeGrape>
            <Plant_Cloudberry>0.02</Plant_Cloudberry>
            <Plant_Berry>0.06</Plant_Berry>
			<Plant_Moss>0.3</Plant_Moss>
            <Plant_PeatMoss>0.1</Plant_PeatMoss>
			<Plant_Blueberry>0.55</Plant_Blueberry>
            <Plant_Daylily>0.2</Plant_Daylily>
			<Plant_Juniper>1.8</Plant_Juniper>
            <Plant_Rhododendron>0.12</Plant_Rhododendron>
			<Plant_Healroot>0.1</Plant_Healroot>
			<Plant_TallGrass>2</Plant_TallGrass>   
            <Plant_Sedge>4</Plant_Sedge>
			<Plant_Astragalus>0.3</Plant_Astragalus>
            <Plant_Bluebell>0.5</Plant_Bluebell>
			<Plant_Anthurium>0.02</Plant_Anthurium>
			<Plant_Crocus>0.6</Plant_Crocus>
			<Plant_Mushroom_Blue>0.02</Plant_Mushroom_Blue>
			<Plant_Mushroom_Red>0.09</Plant_Mushroom_Red>
			<Plant_TreePine>2.0</Plant_TreePine>
			<Plant_TreeSpruce>1.8</Plant_TreeSpruce>
			<Plant_TreeWillow>0.2</Plant_TreeWillow>
            <Plant_Fern>0.1</Plant_Fern>
            <Plant_SwordFern>1</Plant_SwordFern>
		</wildPlants>
		<wildAnimals>
			<Elk>0.8</Elk>
			<Ibex>0.1</Ibex>
			<Caribou>0.6</Caribou>
			<Muffalo>0.4</Muffalo>
			<Squirrel>0.8</Squirrel>
			<WildBoar>0.3</WildBoar>
			<Hare>0.7</Hare>
			<Husky>0.01</Husky>
			<Turkey>0.2</Turkey>
			<Rat>0.5</Rat>
			<Megasloth>0.03</Megasloth>
			<Raccoon>0.6</Raccoon>
			<Warg>0.02</Warg>
			<Bear_Grizzly>0.05</Bear_Grizzly>
			<Rhino_Wooly>0.05</Rhino_Wooly>
			<Cougar>0.02</Cougar>
			<Lynx>0.02</Lynx>
			<Wolf_Timber>0.14</Wolf_Timber>
			<Wolf_Arctic>0.03</Wolf_Arctic>
			<Fox_Arctic>0.04</Fox_Arctic>
			<Fox_Red>0.04</Fox_Red>
			<Fishercat>0.3</Fishercat>
			<Ermine>0.07</Ermine>
			<Megabadger>0.01</Megabadger>
			<Yak>0.12</Yak>
			<Horse_Wooly>0.07</Horse_Wooly>
			<Chipmunk>0.7</Chipmunk>
			<Crashbug>0.7</Crashbug>
			<Ptarmigan>0.6</Ptarmigan>
			<Rimwolf>0.1</Rimwolf>
			<Terramorph>0.05</Terramorph>
			<Sheep>0.2</Sheep>
			<Fly>0.4</Fly>
			<Mosquito>2</Mosquito>
			<WhiteTiger>0.08</WhiteTiger>
			<SnowLeopard>0.07</SnowLeopard>
			<Mammoth>0.04</Mammoth>
			<Cockroach>0.1</Cockroach>
		</wildAnimals>
		<pollutionWildAnimals MayRequire="Ludeon.RimWorld.Biotech">
			<WasteRat MayRequire="Ludeon.RimWorld.Biotech">1</WasteRat>
			<Rat>0.5</Rat>
			<Raccoon>0.25</Raccoon>
			<Warg>0.05</Warg>
			<Crashbug>0.8</Crashbug>
			<Cockroach>0.6</Cockroach>
		</pollutionWildAnimals>
		<allowedPackAnimals>
			<li>Muffalo</li>
			<li>Buffalo</li>
			<li>Horse</li>
			<li>Bear_Grizzly</li>
		</allowedPackAnimals>
	</BiomeDef>
    
    <BiomeDef>
		<defName>MontaneGrasslands</defName>
		<label>montane birch grasslands</label>
		<description>Montane grasslands are high-elevation tundra regions that contain relatively lush wildlife. The cold climate and high winds prevent forest growth, but many species of plant and wildlife can be found here. May contain small ponds and bogs.</description>	
		<workerClass>BiomesKit.UniversalBiomeWorker</workerClass>
        <modExtensions>
            <li Class="BiomesKit.BiomesKitControls">
                  <randomizeHilliness>False</randomizeHilliness>
                  <usePerlin>True</usePerlin>
                  <perlinCulling>0.2</perlinCulling>
                <minElevation>850</minElevation>
                <maxElevation>1500</maxElevation>
                <spawnOnBiomes>
                    <li>BorealForest</li>
                </spawnOnBiomes>
                  <frequency>100</frequency>
            </li>
        </modExtensions>
		<animalDensity>2.0</animalDensity>
		<plantDensity>0.8</plantDensity>
		<settlementSelectionWeight>0.85</settlementSelectionWeight>
		<movementDifficulty>1</movementDifficulty>
		<texture>World/Biomes/MontaneBirch</texture>
		<forageability>0.7</forageability>
		<foragedFood>RawBearberries</foragedFood>
		<wildPlantRegrowDays>25</wildPlantRegrowDays>
		<soundsAmbient>
			<li>Ambient_NightInsects_Standard</li>
		</soundsAmbient>
		<diseaseMtbDays>60</diseaseMtbDays>
		<diseases>
			<li>
				<diseaseInc>Disease_CommonCold</diseaseInc>
				<commonality>100</commonality>
			</li>
			<li>
				<diseaseInc>Disease_strepthroat</diseaseInc>
				<commonality>100</commonality>
			</li>
			<li>
				<diseaseInc>Disease_earache</diseaseInc>
				<commonality>100</commonality>
			</li>
			<li>
				<diseaseInc>Disease_Flu</diseaseInc>
				<commonality>100</commonality>
			</li>
			<li>
				<diseaseInc>Disease_Plague</diseaseInc>
				<commonality>100</commonality>
			</li>
			<li>
				<diseaseInc>Disease_Malaria</diseaseInc>
				<commonality>100</commonality>
			</li>
			<li>
				<diseaseInc>Disease_Fever</diseaseInc>
				<commonality>100</commonality>
			</li>
			<li>
				<diseaseInc>Disease_Measles</diseaseInc>
				<commonality>100</commonality>
			</li>
			<li>
				<diseaseInc>Disease_Ebola</diseaseInc>
				<commonality>20</commonality>
			</li>
			<li>
				<diseaseInc>Disease_Pneumonia</diseaseInc>
				<commonality>50</commonality>
			</li>
			<li>
				<diseaseInc>Disease_FibrousMechanites</diseaseInc>
				<commonality>30</commonality>
			</li>
			<li>
				<diseaseInc>Disease_SensoryMechanites</diseaseInc>
				<commonality>30</commonality>
			</li>
			<li>
				<diseaseInc>Disease_GutWorms</diseaseInc>
				<commonality>50</commonality>
			</li>
			<li>
				<diseaseInc>Disease_MuscleParasites</diseaseInc>
				<commonality>50</commonality>
			</li>
			<li>
				<diseaseInc>Disease_AnimalFlu</diseaseInc>
				<commonality>100</commonality>
			</li>
			<li>
				<diseaseInc>Disease_AnimalPlague</diseaseInc>
				<commonality>100</commonality>
			</li>
		</diseases>
		<terrainsByFertility>
			<!--<li>
				<terrain>Gravel</terrain>
				<min>-999</min>
				<max>0.15</max>
			</li>
			<li>
				<terrain>RockySoil</terrain>
				<min>0.15</min>
				<max>0.3</max>
			</li>
            <li>
				<terrain>PrairieSoil</terrain>
				<min>0.3</min>
				<max>999</max>
			</li>
   -->
            <li>
				<terrain>PoorSoil</terrain>
				<min>-999</min>
				<max>0.25</max>
			</li>
			<li>
				<terrain>MossyTerrain</terrain>
				<min>0.25</min>
				<max>0.5</max>
			</li>
            <li>
				<terrain>PrairieSoil</terrain>
				<min>0.5</min>
				<max>999</max>
			</li>
		</terrainsByFertility>
		<terrainPatchMakers>
             <li>
				<perlinFrequency>0.02</perlinFrequency>
				<thresholds>
					<li>
						<terrain>Gravel</terrain>
						<min>0.8</min>
						<max>0.95</max>
					</li>
                    <li>
                        <terrain>RockySoil</terrain>
                        <min>0.95</min>
                        <max>999</max>
                    </li>
				</thresholds>
			</li>
            
            
            <li>
				<perlinFrequency>0.015</perlinFrequency>
				<thresholds>
					<li>
						<terrain>PeatSoil</terrain>
						<min>0.95</min>
						<max>1</max>
					</li>
                    <li>
						<terrain>BogWater</terrain>
						<min>1</min>
						<max>999</max>
					</li>
				</thresholds>
			</li>
            
			<li>
				<perlinFrequency>0.03</perlinFrequency>
				<thresholds>
					<li>
						<terrain>SoilRich</terrain>
						<min>0.6</min>
						<max>0.7</max>
					</li>
					<li>
						<terrain>WaterShallow</terrain>
						<min>0.7</min>
						<max>0.8</max>
					</li>
                    <li>
						<terrain>WaterDeep</terrain>
						<min>0.8</min>
						<max>999</max>
					</li>
				</thresholds>
			</li>
		</terrainPatchMakers>
		<baseWeatherCommonalities>
			<Clear>15</Clear>
			<Fog>4</Fog>
			<Rain>4</Rain>
			<DryThunderstorm>1</DryThunderstorm>
			<RainyThunderstorm>2</RainyThunderstorm>
			<FoggyRain>3</FoggyRain>
			<SnowGentle>4</SnowGentle>
			<SnowHard>4</SnowHard>
			<Rainstorm>3</Rainstorm>
			<Blizzard>4</Blizzard>
			<Whiteout>4</Whiteout>
			<Hurricane>0.1</Hurricane>
		</baseWeatherCommonalities>
		<wildPlants>
            <Plant_Cloudberry>0.7</Plant_Cloudberry>
            <Plant_Bearberry>0.2</Plant_Bearberry>
			<Plant_Moss>2</Plant_Moss>
            <Plant_PeatMoss>0.5</Plant_PeatMoss>
			<Plant_Blueberry>0.25</Plant_Blueberry>
            <Plant_Daylily>0.2</Plant_Daylily>
			<Plant_Juniper>0.9</Plant_Juniper>
            <Plant_Bush>0.7</Plant_Bush>
            <Plant_Rhododendron>0.12</Plant_Rhododendron>
			<Plant_Healroot>0.1</Plant_Healroot>
			<Plant_Sedge>8</Plant_Sedge>   
            <Plant_Grass>4</Plant_Grass>
            <Plant_TallGrass>1</Plant_TallGrass>
			<Plant_Astragalus>0.3</Plant_Astragalus>
            <Plant_Bluebell>0.85</Plant_Bluebell>
			<Plant_Anthurium>0.01</Plant_Anthurium>
			<Plant_Crocus>0.3</Plant_Crocus>
			<Plant_Mushroom_Blue>0.08</Plant_Mushroom_Blue>
			<Plant_Mushroom_Red>0.02</Plant_Mushroom_Red>
			<Plant_TreeBirch>0.8</Plant_TreeBirch>
            <Plant_TreeSpruce>0.15</Plant_TreeSpruce>
			<Plant_TreeDwarfWillow>0.3</Plant_TreeDwarfWillow>
            <Plant_Fern>0.1</Plant_Fern>
            <Plant_SwordFern>0.4</Plant_SwordFern>
		</wildPlants>
		<wildAnimals>
			<Elk>0.7</Elk>
			<Caribou>1.2</Caribou>
			<Muffalo>0.8</Muffalo>
			<Squirrel>0.8</Squirrel>
			<WildBoar>0.1</WildBoar>
			<Hare>0.7</Hare>
			<Husky>0.01</Husky>
			<Turkey>0.2</Turkey>
			<Rat>0.5</Rat>
			<Megasloth>0.03</Megasloth>
			<Raccoon>0.6</Raccoon>
			<Warg>0.02</Warg>
			<Bear_Grizzly>0.05</Bear_Grizzly>
			<Rhino_Wooly>0.05</Rhino_Wooly>
			<Cougar>0.02</Cougar>
			<Lynx>0.02</Lynx>
			<Wolf_Timber>0.03</Wolf_Timber>
			<Wolf_Arctic>0.08</Wolf_Arctic>
			<Fox_Arctic>0.15</Fox_Arctic>
			<Fishercat>0.3</Fishercat>
			<Megabadger>0.01</Megabadger>
			<Yak>0.05</Yak>
			<Horse_Wooly>0.09</Horse_Wooly>
			<Chipmunk>0.7</Chipmunk>
			<Crashbug>0.7</Crashbug>
			<Ptarmigan>0.8</Ptarmigan>
			<Rimwolf>0.1</Rimwolf>
			<Terramorph>0.05</Terramorph>
			<Sheep>0.3</Sheep>
			<Fly>0.4</Fly>
			<Mosquito>1</Mosquito>
			<WhiteTiger>0.08</WhiteTiger>
			<SnowLeopard>0.07</SnowLeopard>
			<Mammoth>0.09</Mammoth>
			<Cockroach>0.1</Cockroach>
		</wildAnimals>
		<pollutionWildAnimals MayRequire="Ludeon.RimWorld.Biotech">
			<WasteRat MayRequire="Ludeon.RimWorld.Biotech">1</WasteRat>
			<Rat>0.5</Rat>
			<Raccoon>0.25</Raccoon>
			<Warg>0.05</Warg>
			<Crashbug>0.8</Crashbug>
			<Cockroach>0.6</Cockroach>
		</pollutionWildAnimals>
		<allowedPackAnimals>
			<li>Muffalo</li>
			<li>Buffalo</li>
			<li>Horse</li>
			<li>Bear_Grizzly</li>
		</allowedPackAnimals>
	</BiomeDef>
</Defs>
